pyfolio/__init__.py
pyfolio/_seaborn.py
pyfolio/bayesian.py
pyfolio/capacity.py
pyfolio/deprecate.py
pyfolio/interesting_periods.py
pyfolio/ipycompat.py
pyfolio/perf_attrib.py
pyfolio/plotting.py
pyfolio/pos.py
pyfolio/risk.py
pyfolio/round_trips.py
pyfolio/tears.py
pyfolio/timeseries.py
pyfolio/txn.py
pyfolio/utils.py
pyfolio_tekton-1.3.dist-info/METADATA
pyfolio_tekton-1.3.dist-info/WHEEL
pyfolio_tekton-1.3.dist-info/top_level.txt
pyfolio_tekton-1.3.dist-info/RECORD
