Metadata-Version: 2.1
Name: pyfolio-tekton
Version: 1.3
Summary: PyFolio Tekton
Author: Quantopian and Everton Mendes
Author-email: emendes@tektonfinance.com
Requires-Dist: pyfolio (>=0.9.2)
